STAIR/ABA_annotation.py
STAIR/__init__.py
STAIR/emb_alignment.py
STAIR/loc_alignment.py
STAIR/loc_prediction.py
STAIR/utils.py
STAIR/ABAanno/__init__.py
STAIR/ABAanno/ontology.csv
STAIR/ABAanno/ontology1.pkl
STAIR/ABAanno/ontology1_reverse.pkl
STAIR/ABAanno/ontology2.pkl
STAIR/ABAanno/ontology2_reverse.pkl
STAIR/ABAanno/ontology_level1.csv
STAIR/ABAanno/ontology_level2.csv
STAIR/ABAanno/ontology_level3.csv
STAIR/ABAanno/ccfv3/annotation_100.nrrd
STAIR/ABAanno/ccfv3/annotation_25.nrrd
STAIR/ABAanno/ccfv3/annotation_50.nrrd
STAIR/embedding/__init__.py
STAIR/embedding/dataset_ae.py
STAIR/embedding/dataset_hgat.py
STAIR/embedding/loss.py
STAIR/embedding/module_ae.py
STAIR/embedding/module_hgat.py
STAIR/embedding/module_hgat1.py
STAIR/location/__init__.py
STAIR/location/align_fine.py
STAIR/location/align_init.py
STAIR/location/edge_detection.py
STAIR/location/edge_detection1.py
STAIR/location/transformation.py
STAIR_tools-1.3.1.dist-info/METADATA
STAIR_tools-1.3.1.dist-info/WHEEL
STAIR_tools-1.3.1.dist-info/top_level.txt
STAIR_tools-1.3.1.dist-info/RECORD
