Metadata-Version: 2.1
Name: STAIR-tools
Version: 1.3.1
Summary: Spatial Transcriptomic Alignment, Integration, and de novo 3D Reconstruction
Home-page: UNKNOWN
Author: yuanyuanyu
Author-email: UNKNOWN
License: MIT
Platform: UNKNOWN
